example/tensorflow_on_flink_table.py
example/__init__.py
flink_ml_tensorflow/gpu_info.py
flink_ml_tensorflow/libflink_ops.so
flink_ml_tensorflow/tfrecord_table_source.py
flink_ml_tensorflow/tensorflow_context.py
flink_ml_tensorflow/tensorflow_on_flink_tfconf.py
flink_ml_tensorflow/tfrecord_source_func.py
flink_ml_tensorflow/tensorflow_TFConfig.py
flink_ml_tensorflow/table_sinks.py
flink_ml_tensorflow/tensorflow_on_flink_table.py
flink_ml_tensorflow/__init__.py
flink_ml_tensorflow/tensorflow_on_flink_mlconf.py
flink_ml_tensorflow/tensorflow_on_flink_ops.py
flink_ml_tensorflow/version.py
flink_ml_tensorflow_2.x-0.4.dev20220209.dist-info/METADATA
flink_ml_tensorflow_2.x-0.4.dev20220209.dist-info/top_level.txt
flink_ml_tensorflow_2.x-0.4.dev20220209.dist-info/RECORD
flink_ml_tensorflow_2.x-0.4.dev20220209.dist-info/WHEEL
