Metadata-Version: 2.1
Name: flink-ml-tensorflow-2.x
Version: 0.4.dev20220209
Summary: UNKNOWN
Home-page: https://github.com/flink-extended/dl-on-flink
License: https://www.apache.org/licenses/LICENSE-2.0
Platform: UNKNOWN
Requires-Python: >=3.7,<3.9
Requires-Dist: tensorflow (<2.4.0,>=2.3.1)
Requires-Dist: tensorboard (<2.4.0,>=2.3.0)
Requires-Dist: apache-flink (<1.15.0,>=1.14.0)
Requires-Dist: flink-ml-framework (==0.4.dev20220209)
